custom_glue/__init__.py
custom_glue/_nbdev.py
custom_glue/core.py
nbdev_template/__init__.py
nbdev_template/_nbdev.py
nbdev_template/core.py
custom_glue-0.0.6.dist-info/LICENSE
custom_glue-0.0.6.dist-info/METADATA
custom_glue-0.0.6.dist-info/WHEEL
custom_glue-0.0.6.dist-info/entry_points.txt
custom_glue-0.0.6.dist-info/top_level.txt
custom_glue-0.0.6.dist-info/RECORD
